chios/__init__.py
chios/bolditalic/__init__.py
chios/bolditalic/bolditalic.css
chios/remotecode/__init__.py
chios/remoteinclude/__init__.py
chios-1.0.0.dist-info/LICENSE
chios-1.0.0.dist-info/METADATA
chios-1.0.0.dist-info/WHEEL
chios-1.0.0.dist-info/top_level.txt
chios-1.0.0.dist-info/RECORD
