Metadata-Version: 2.1
Name: chios
Version: 1.0.0
Summary: A collection of Sphinx extensions.
Home-page: https://github.com/kallimachos/chios
Author: Brian moss
Author-email: kallimachos@gmail.com
License: GPLv3
Keywords: sphinx documentation extension bold italic remote code
Platform: UNKNOWN
Classifier: Development Status :: 5 - Production/Stable
Classifier: Intended Audience :: Developers
Classifier: Topic :: Documentation :: Sphinx
Classifier: Framework :: Sphinx :: Extension
Classifier: License :: OSI Approved :: GNU General Public License v3 (GPLv3)
Classifier: Programming Language :: Python :: 3
Classifier: Programming Language :: Python :: 3.7
Classifier: Programming Language :: Python :: 3.8
Classifier: Programming Language :: Python :: 3.9
License-File: LICENSE
Requires-Dist: docutils
Requires-Dist: requests
Requires-Dist: sphinx
